[
  {
    "title": "白紵辭",
    "author": "李丙",
    "content": [
      "嬌如花，美如玉，越溪女兒十五六。",
      "光風入簾睡初足，起畫修眉遠山綠。",
      "飛香走紅三月心，一聲白紵千黄金。",
      "高堂客散燈火深，醉鬢斜釵夜沈沈。"
    ]
  },
  {
    "title": "別趙常德",
    "author": "趙蕃",
    "content": [
      "舊詩零落似前生，豈意公能識姓名。",
      "青眼何堪辱如故，白頭自覺已無成。",
      "普天無復歸耕處，薄祿謾爲餬口營。",
      "今日違離定何往，壺頭路險更秦城。"
    ]
  },
  {
    "title": "白紵詞",
    "author": "郭晞宗",
    "content": [
      "遥夜迢迢夜未央，井梧月色啼寒螿，感時念往誰不傷。",
      "婕妤寵絕辭昭陽，手中團扇篋中藏。",
      "吳姬織紵秋蟬翼，一絲往復千情積。",
      "金粟尺量金斗熨，爲君裁袍爲君惜，同盛同衰莫相失。"
    ]
  },
  {
    "title": "白紵詞",
    "author": "葉適",
    "content": [
      "有美一人兮表獨處，陟彼南山兮伐寒紵。",
      "挑燈細緝抽苦心，冰花織成雪爲縷。",
      "不憂絕技無人學，只愁不堪嫁時著。",
      "鄭僑吳札今悠悠，爭看買笑錦纏頭。"
    ]
  },
  {
    "title": "白紵詞",
    "author": "翁卷",
    "content": [
      "翩翩長袖光閃銀，繡羅帳密流香塵。",
      "歌分四時舞一色，淥觴傳處馳金輪。",
      "急竹繁絲互催逼，吳娘嬌濃玉無力。",
      "呵星喚月留夜長，十二圍屏暖山色。"
    ]
  },
  {
    "title": "拜總持尼祖塔",
    "author": "釋居簡",
    "content": [
      "平生自愛黄金膝，肯屈榛蕪草棘深。",
      "弗似灌溪閑上座，尼壇再展不同心。"
    ]
  },
  {
    "title": "別子陳子",
    "author": "華岳",
    "content": [
      "丙寅三月三十日，天子檄我南國行。",
      "蒲劍欲飛春漲急，柳綿才脫曉寒輕。",
      "事非得已初何好，物到不平終作聲。",
      "自古英雄總多難，賈梁何必怨清明。"
    ]
  },
  {
    "title": "病中酬趙季茂",
    "author": "岳珂",
    "content": [
      "雪窗病惱獨支頤，不解隨人舉酒巵。",
      "驚辨有時欺白羽，解圍無婦蔽青絲。",
      "驪珠滿袖勾吟興，鹿氅看山戀藥糜。",
      "莫訝牛腰聯未足，江州司馬例能詩。"
    ]
  },
  {
    "title": "跋張敞畫眉圖",
    "author": "劉克莊",
    "content": [
      "列岫新眉淡復濃，黛螺百斛不堪供。",
      "迴頭却笑張京兆，只掃閨中兩點峰。"
    ]
  },
  {
    "title": "別張倅一首",
    "author": "劉克莊",
    "content": [
      "同謁金閨覲茂陵，鼎湖弓劍隔西興。",
      "絕憐晚景如龐老，空爲州人惜許丞。",
      "自有名姬調綠綺，可無侍女直青綾。",
      "夢中雪鼓攙天碧，恨不陪君拄瘦藤。"
    ]
  },
  {
    "title": "別子才司令",
    "author": "方岳",
    "content": [
      "不如意事常八九，可與語人無二三。",
      "自識荆門子才甫，夢馳鐵馬戰城南。"
    ]
  },
  {
    "title": "病中酬王尉",
    "author": "方岳",
    "content": [
      "造物無何亦小兒，一生心事只山知。",
      "江湖晚歲勤行李，風雨重陽倒接䍦。",
      "硯老自研明月露，蟹香新在菊花時。",
      "與君共住維摩室，何日重携鶴膝枝。"
    ]
  },
  {
    "title": "別贈陳新叔弟",
    "author": "趙孟堅",
    "content": [
      "神靈造天極，仁深祚綿遠。",
      "光堯渡江初，屬族扶日輦。",
      "南來逾百年，瓜瓞載繁衍。",
      "開江一枝燈，海濱發長燄。",
      "紹興庚辰第，伯祖維創見。",
      "自此燈燈續，儒科已累踐。",
      "姪也幼則孤，門戶中屯蹇。",
      "執編青衿後，浪策禮部選。",
      "有叔行派親，隔驀此異閈。",
      "天都邂逅初，覿面苦恨晚。",
      "爲言起家難，銖積勤靡倦。",
      "相從忽問勞，把臂互驚嘆。",
      "霅城每頻過，訪我李曹掾。",
      "及茲脫選海，幾擬謝深眷。",
      "三年在奔波，留滯顔色靦。",
      "扁舟此經從，相見笑而莞。",
      "排日羅酒漿，延顧禮既腆。",
      "所欣廷蘭秀，一一莫可揀。",
      "讀書固有獲，而况多積善。",
      "竇桂未足誇，王槐定應顯。",
      "願言闡宏規，涵肆觀文典。",
      "士業止科名，耕耨工亦淺。",
      "胸中澆萬卷，落筆自精悍。",
      "何當它年來，大雅見文憲。",
      "功名固懸命，立志毋狹褊。",
      "微言勿謂迂，聊作友于勉。"
    ]
  },
  {
    "title": "別趙丞",
    "author": "何文季",
    "content": [
      "花縣平分月，冰壺不受塵。",
      "圓機皆中理，禮愛獨親仁。",
      "晚菊長留節，寒梅自作春。",
      "無家可歸去，須有築臺人。"
    ]
  },
  {
    "title": "白紵詞",
    "author": "吳龍翰",
    "content": [
      "吴宫烟水碧迢迢，瓊樓十二凌青霄。",
      "北方佳人顔如花，素衣濯濯明朝霞。",
      "雲母屏風珍珠箔，香銷金鴨春寒薄。",
      "璧月流光羅綺筵，白紵舞殘月欲落。",
      "君看月落夜潮平，吴江濶兮越江深。",
      "吴王醉兮越王醒。"
    ]
  },
  {
    "title": "丙子除夜",
    "author": "戴表元",
    "content": [
      "富貴如今似駭機，漂流未遣壯心違。",
      "鄉鄰有酒貧能醉，村落無醫病亦稀。",
      "客任低頭從狗竇，妻休掩面對牛衣。",
      "十年涉世渾如此，除却躬耕事事非。"
    ]
  },
  {
    "title": "別諸禪衆",
    "author": "釋洪海",
    "content": [
      "萬瓦禪林聳翠螺，四圍山色玉新磨。",
      "恍疑別換胸懷子，霽月光風覺轉多。"
    ]
  },
  {
    "title": "伯鎮出都後見寄",
    "author": "劉敞",
    "content": [
      "疉鼓鳴笳太守船，都人傾注似登仙。",
      "舊遊俯仰成陳迹，離思紛紜遶别絃。",
      "愁目青楓空自極，素書雙鯉不忘傳。",
      "恐君未得江湖樂，追詔方将急用賢。"
    ]
  },
  {
    "title": "别張從道",
    "author": "韋驤",
    "content": [
      "官居相並日相過，盈歲光陰不覺多。",
      "每幸開心互詢度，都忘倦跡久蹉跎。",
      "新除忽遂東歸欲，雅好其如遠别何。",
      "把酒不辭金盞溢，預將離索就消磨。"
    ]
  },
  {
    "title": "別諸禪衆  其一",
    "author": "向宗道",
    "content": [
      "四絕之名豈浪傳，千巖萬石五雲間。",
      "無才可述無窮景，祇愛真山似假山。"
    ]
  },
  {
    "title": "別諸禪衆  其二",
    "author": "向宗道",
    "content": [
      "古殿瑯璫木魚響，匆匆策馬長松間。",
      "迴頭卻恨歸時早，月淡煙昏不見山。"
    ]
  },
  {
    "title": "白紵辭上蘇翰林二首  其一",
    "author": "晁補之",
    "content": [
      "白紵棼莫緝，紉蘭作衣袪。",
      "朝兮日所暴，暮兮雨所濡。",
      "木瓜諒微物，期報乃瓊琚。",
      "芳華辭甚妙，贈我不如無。"
    ]
  },
  {
    "title": "白紵辭上蘇翰林二首  其二",
    "author": "晁補之",
    "content": [
      "上山割白紵，山高葉摵摵。",
      "持歸當戶績，爲君爲絺綌。",
      "不惜潔如霜，畏君莫我即。",
      "誰言菖蒲花，可聞不可識。"
    ]
  },
  {
    "title": "白紵詞二首效鮑照  其一",
    "author": "張耒",
    "content": [
      "摇輕裾，曳長袖，爲楚舞，千萬壽。",
      "新詞白紵聲按舊。",
      "朔風捲地來崢嶸，燕雁避霜饑不鳴。",
      "高堂酒多華燈明。"
    ]
  },
  {
    "title": "白紵詞二首效鮑照  其二",
    "author": "張耒",
    "content": [
      "回纖腰，出素手，髻墮鬢傾釵欲溜，爲君歌舞君飲酒。",
      "歲云暮矣七澤空，湯湯漢沔天北風。",
      "玉壺之酒樂未終。"
    ]
  },
  {
    "title": "寶誌禪師梁天監中將入寂然一燭付後閣舍人吳慶慶以事聞帝歎曰大師不復留矣燭者將以後事囑我乎頌",
    "author": "饒節",
    "content": [
      "已是梁王不識真，末後殷勤付舍人。",
      "柳花飛盡鶑猶語，獨對鍾山指暮雲。"
    ]
  },
  {
    "title": "跋趙朝議江行初雪圖",
    "author": "陳克",
    "content": [
      "我本孤舟蓑笠翁，雪厓烟樹一生中。",
      "如今不向江湖去，鬬艦旌旗照水紅。"
    ]
  },
  {
    "title": "病中春盡言懷",
    "author": "員興宗",
    "content": [
      "萬象無涯春有涯，愁腸幾逐夢魂賒。",
      "解吟整整堂堂句，勝看紅紅白白花。"
    ]
  },
  {
    "title": "病中曾端伯見訪",
    "author": "呂本中",
    "content": [
      "不見倉曹十五年，江城相遇各華顛。",
      "何時更踐隣居約，判斷諸方五味禪。",
      "浮生擾擾亂初定，久病昏昏閑始便。",
      "欲問小童尋大隗，勝于猛將畫凌烟。"
    ]
  },
  {
    "title": "病中初見梅花馳送季申樞密併以二絕  其一",
    "author": "李彌遜",
    "content": [
      "老幹疏枝不耐冬，喜聞芳信擾青紅。",
      "應緣技癢争春力，不待鉛華破曉風。"
    ]
  },
  {
    "title": "病中初見梅花馳送季申樞密併以二絕  其二",
    "author": "李彌遜",
    "content": [
      "病眼逢花不忍窺，飛奴走送已嫌遲。",
      "定知着意憐纖瘦，不放春心落别枝。"
    ]
  },
  {
    "title": "病中酬元宗簡",
    "author": "張籍",
    "content": [
      "東風漸暖滿城春，獨占幽居養病身。",
      "莫說櫻桃花已發，今年不作看花人。"
    ]
  },
  {
    "title": "邠州詞獻高尚書三首 一",
    "author": "李涉",
    "content": [
      "單于都護再分疆，西引雙旌出帝鄉。",
      "朝日詔書添戰馬，即聞千騎取河湟。"
    ]
  },
  {
    "title": "邠州詞獻高尚書三首 二",
    "author": "李涉",
    "content": [
      "將家難立是威聲，不見多傳衛霍名。",
      "一自元和平蜀後，馬頭行處即長城。"
    ]
  },
  {
    "title": "邠州詞獻高尚書三首 三",
    "author": "李涉",
    "content": [
      "朔方忠義舊來閑，盡是邠城父子軍。",
      "今日兵符歸上將，旄頭不用更妖氛。"
    ]
  },
  {
    "title": "汴州船行賦岸傍所見",
    "author": "沈亞之",
    "content": [
      "古木曉蒼蒼，秋林拂岸香。",
      "露珠蟲網細，金縷兔絲長。",
      "秋浪時迴沫，驚鱗乍觸航。",
      "蓬煙拈綠線，棘實綴紅囊。",
      "亂穗搖鼯尾，出根挂鳳腸。",
      "聊持一濯足，誰道比滄浪。"
    ]
  },
  {
    "title": "病中晨起即事寄場中往還",
    "author": "劉得仁",
    "content": [
      "昨日離塵裏，今朝懶已成。",
      "豈能爲久隱，更欲泥浮名。",
      "虛牖晨光白，幽園曉氣清。",
      "戴沙尋水去，披霧入林行。",
      "疊葉孤禽在，初陽半樹明。",
      "桑麻新雨潤，蘆荻古波聲。",
      "易向田家熟，元于世路生。",
      "病多三徑塞，吟苦四鄰驚。"
    ]
  },
  {
    "title": "斑竹祠",
    "author": "汪遵",
    "content": [
      "九處煙霞九處昏，一回延首一銷魂。",
      "因憑直節流紅淚，圖得千秋見血痕。"
    ]
  },
  {
    "title": "病中初聞復官二首 一",
    "author": "韓偓",
    "content": [
      "抽毫連夜侍明光，執靮三年從省方。",
      "燒玉謾勞曾歷試，鑠金寧爲欠周防。",
      "也知恩澤招讒口，還痛神祇誤直腸。",
      "聞道復官飜涕泗，屬車何在水茫茫。"
    ]
  },
  {
    "title": "病中初聞復官二首 二",
    "author": "韓偓",
    "content": [
      "又挂朝衣一自驚，始知天意重推誠。",
      "青雲有路通還去，白髮無私健亦生。",
      "曾避暖池將浴鳳，却同寒谷乍遷鶯。",
      "宦途巇嶮終難測，穩泊漁舟隱姓名。"
    ]
  },
  {
    "title": "病中春日即事寄主人尚書二首 一",
    "author": "徐夤",
    "content": [
      "身比秋荷覺漸枯，至君經國墮前圖。",
      "層冰照日猶能暖，病骨逢春却未蘇。",
      "鏡裏白鬚撏又長，枝頭黃鳥靜還呼。",
      "庾樓恩化通神聖，何計能教擲得盧。"
    ]
  },
  {
    "title": "病中春日即事寄主人尚書二首 二",
    "author": "徐夤",
    "content": [
      "風拍衰肌久未蠲，破窗頻見月團圓。",
      "更無舊日同人問，只有多情太守憐。",
      "臘內送將三折股，歲陰分與五銖錢。",
      "玄穹若假年齡在，願捧銅盤爲國賢。"
    ]
  },
  {
    "title": "白紵辭 一",
    "author": "楊衡",
    "content": [
      "玉纓翠珮雜輕羅，香汗微漬朱顏酡，爲君起唱白紵歌。",
      "清聲褭雲思繁多，凝笳哀琴時相和。",
      "金壺半傾芳夜促，梁塵霏霏暗紅燭。",
      "令君安坐聽終曲，墜葉飄花難再復。"
    ]
  },
  {
    "title": "白紵辭 二",
    "author": "楊衡",
    "content": [
      "躡珠履，步瓊筵。",
      "輕身起舞紅燭前，芳姿豔態妖且妍。",
      "迴眸轉袖暗催弦，涼風蕭蕭漏水急。",
      "月華泛溢紅蓮濕，牽裙攬帶翻成泣。"
    ]
  },
  {
    "title": "百子池",
    "author": "張諤",
    "content": [
      "舊聞百子漢家池，漢家淥水今逶迤。",
      "宮女厭鏡笑窺池，身前影後不相見。"
    ]
  },
  {
    "title": "白紵辭二首 一",
    "author": "崔國輔",
    "content": [
      "洛陽梨花落如霰，河陽桃葉生復齊。",
      "坐惜玉樓春欲盡，紅綿粉絮裛妝啼。"
    ]
  },
  {
    "title": "白紵辭二首 二",
    "author": "崔國輔",
    "content": [
      "董賢女弟在椒風，窈窕繁華貴後宮。",
      "璧帶金釭皆翡翠，一朝零落變成空。"
    ]
  },
  {
    "title": "白紵辭三首 一",
    "author": "李白",
    "content": [
      "揚清歌，發皓齒，北方佳人東隣子。",
      "且吟白紵停綠水，長袖拂面爲君起。",
      "寒雲夜卷霜海空，胡風吹天飄塞鴻。",
      "玉顏滿堂樂未終，館娃日落歌吹濛。"
    ]
  },
  {
    "title": "白紵辭三首 二",
    "author": "李白",
    "content": [
      "月寒江清夜沈沈，美人一笑千黃金。",
      "垂羅舞縠揚哀音，郢中白雪且莫吟。",
      "子夜吳歌動君心，動君心，冀君賞。",
      "願作天池雙鴛鴦，一朝飛去青雲上。"
    ]
  },
  {
    "title": "白紵辭三首 三",
    "author": "李白",
    "content": [
      "吳刀剪綵縫舞衣，明妝麗服奪春暉。",
      "揚眉轉袖若雪飛，傾城獨立世所稀。",
      "激楚結風醉忘歸，高堂月落燭已微，玉釵挂纓君莫違。"
    ]
  },
  {
    "title": "比作陳下瓜麴釀成奇絕屬病瘍不敢取醉小啜而已",
    "author": "陸游",
    "content": [
      "翠蔓扶疏采擷忙，麴生糸出古淮陽。",
      "蹋成明月團團白，釀作新鵝淡淡黄。",
      "醅甕秋凄驚凛冽，糟床夜注愛淋浪。",
      "西齋幽事新成譜，首爲高人著此方。"
    ]
  },
  {
    "title": "病中春雨聞東園花盛",
    "author": "楊萬里",
    "content": [
      "萬類欣欣一老悲，物華豈是不佳時。",
      "病夫自與春無分，好景非於我獨遺。",
      "花底報來開已閙，雨中過了更曾知。",
      "風光九十今强半，又約芳菲隔歲期。"
    ]
  },
  {
    "title": "病中次務觀通判韻",
    "author": "周必大",
    "content": [
      "老眼亂蟬翼，樂事歎何有。",
      "經年不銜杯，更暇問濡首。",
      "愛山空在山，擿埴詎容走。",
      "塵埃登高帽，生澀彈棋手。",
      "三年一蒲團，近者坐欲朽。",
      "朝來獨何事，乾鵲窺甕牖。",
      "開門得新詩，刮膜如釋負。",
      "卷舒幾百回，呼舞駭鄰友。",
      "吾曹交以淡，悠久或采韭。",
      "此味只自知，他人薄玄酒。"
    ]
  },
  {
    "title": "病中呈諸友",
    "author": "朱熹",
    "content": [
      "窮居值秋晦，抱疾獨齋居。",
      "行稀草生徑，一雨復旬餘。",
      "交親各所營，曠若音塵踈。",
      "始悟端居樂，復理北窗書。",
      "讀誦興已闌，起坐方躊躇。",
      "綠樹滿空庭，策策飊初。",
      "良時不復停，煩吝未云祛。",
      "還思對君子，日夕佇軒車。"
    ]
  },
  {
    "title": "病中承子服老弟同居厚叔通居中居晦諸兄友載酒見過子服有詩牽勉奉和并呈在席幸發一笑",
    "author": "朱熹",
    "content": [
      "心期萬壑與千巖，屢向君詩得指南。",
      "久恨泠然孤宿諾，偶逢兀者便同參。",
      "儻蒙大藥分金匕，豈羨奇方出玉函。",
      "誰識留連今夕意，沈痾未散莫回驂。"
    ]
  },
  {
    "title": "百子池",
    "author": "張諤",
    "content": [
      "舊聞百子漢家池，漢家淥水今逶迤。宮女厭鏡笑窺池，"
    ]
  },
  {
    "title": "白紵辭三首",
    "author": "李白",
    "content": [
      "揚清歌，發皓齒，北方佳人東鄰子。且吟白紵停綠水，",
      "玉顏滿堂樂未終，館娃日落歌吹蒙。",
      "月寒江清夜沉沉，美人一笑千黃金。垂羅舞縠揚哀音，",
      "願作天池雙鴛鴦，一朝飛去青雲上。",
      "吳刀剪綵縫舞衣，明妝麗服奪春暉。揚眉轉袖若雪飛，"
    ]
  },
  {
    "title": "病中酬元宗簡",
    "author": "張籍",
    "content": [
      "東風漸暖滿城春，獨佔幽居養病身。",
      "莫說櫻桃花已發，今年不作看花人。"
    ]
  },
  {
    "title": "邠州詞獻高尚書三首",
    "author": "李涉",
    "content": [
      "單于都護再分疆，西引雙旌出帝鄉。",
      "朝日詔書添戰馬，即聞千騎取河湟。",
      "將家難立是威聲，不見多傳衛霍名。",
      "一自元和平蜀後，馬頭行處即長城。",
      "朔方忠義舊來聞，儘是邠城父子軍。",
      "今日兵符歸上將，旄頭不用更妖氛。"
    ]
  },
  {
    "title": "汴州船行賦岸傍所見",
    "author": "沈亞之",
    "content": [
      "古木曉蒼蒼，秋林拂岸香。露珠蟲網細，金縷兔絲長。",
      "秋浪時回沫，驚鱗乍觸航。蓬煙拈綠線，棘實綴紅囊。",
      "亂穗搖鼯尾，出根掛鳳腸。聊持一濯足，誰道比滄浪。"
    ]
  },
  {
    "title": "病中晨起即事寄場中往還",
    "author": "劉得仁",
    "content": [
      "昨日離塵裏，今朝懶已成。豈能為久隱，更欲泥浮名。",
      "虛牖晨光白，幽園曉氣清。戴沙尋水去，披霧入林行。",
      "疊葉孤禽在，初陽半樹明。桑麻新雨潤，蘆荻古波聲。",
      "易向田家熟，元于世路生。病多三徑塞，吟苦四鄰驚。"
    ]
  },
  {
    "title": "斑竹祠",
    "author": "汪遵",
    "content": [
      "九處煙霞九處昏，一回延首一銷魂。",
      "因憑直節流紅淚，圖得千秋見血痕。"
    ]
  },
  {
    "title": "病中初聞複官二首",
    "author": "韓偓",
    "content": [
      "抽毫連夜侍明光，執靮三年從省方。燒玉謾勞曾曆試，",
      "聞道複官翻涕泗，屬車何在水茫茫。",
      "又掛朝衣一自驚，始知天意重推誠。青雲有路通還去，",
      "宦途巇嶮終難測，穩泊漁舟隱姓名。"
    ]
  },
  {
    "title": "病中春日即事寄主人尚書二首",
    "author": "徐夤",
    "content": [
      "身比秋荷覺漸枯，致君經國墮前圖。層冰照日猶能暖，",
      "庾樓恩化通神聖，何計能教擲得盧。",
      "風拍衰肌久未蠲，破窗頻見月團圓。更無舊日同人問，",
      "玄穹若假年齡在，願捧銅盤為國賢。"
    ]
  },
  {
    "title": "白紵辭",
    "author": "楊衡",
    "content": [
      "玉纓翠佩雜輕羅，香汗微漬朱顏酡。為君起唱白紵歌，",
      "躡珠履，步瓊筵，輕身起舞紅燭前。芳姿豔態妖且妍，"
    ]
  },
  {
    "title": "宾之初筵",
    "author": "",
    "content": [
      "宾之初筵，左右秩秩。笾豆有楚，殽核维旅。酒既和旨，饮酒孔偕。",
      "钟鼓既设，举酬逸逸。大侯既抗，弓矢斯张。射夫既同，献尔发功。",
      "发彼有的，以祈尔爵。",
      "籥舞笙鼓，乐既和奏。烝衎烈祖，以洽百礼。百礼既至，有壬有林。",
      "锡尔纯嘏，子孙其湛。其湛曰乐，各奏尔能。宾载手仇，室人入又。",
      "酌彼康爵，以奏尔时。",
      "宾之初筵，温温其恭。其未醉止，威仪反反。曰既醉止，威仪幡幡。",
      "舍其坐迁，屡舞仙仙。其未醉止，威仪抑抑。曰既醉止，威仪抑抑。",
      "是曰既醉，不知其秩。",
      "宾既醉止，载号载呶。乱我笾豆，屡舞僛僛。是曰既醉，不知其邮。",
      "侧弁之俄，屡舞傞傞。既醉而出，并受其福。醉而不出，是谓伐德。",
      "饮酒孔嘉，维其令仪。",
      "凡此饮酒，或醉或否。既立之监，或佐之史。彼醉不臧，不醉反耻。",
      "式勿从谓，无俾大怠。匪言勿言，匪由勿语。由醉之言，俾出童羖。",
      "三爵不识，矧敢多又。"
    ],
    "meta": {
      "chapter": "小雅",
      "section": "甫田之什"
    }
  }
]