[
  {
    "title": "讀王文公詩",
    "author": "許及之",
    "content": [
      "文章與世爲師範，經術於時起世仇。",
      "少讀公詩頭已白，只因無奈句風流。"
    ]
  },
  {
    "title": "讀五王傳",
    "author": "石介",
    "content": [
      "聖賢用策寧相遠，千載毫釐竟不差。",
      "四皓當年安漢嗣，五王今日復唐家。"
    ]
  },
  {
    "title": "代王維謹挽李察院二首  其一",
    "author": "黄榦",
    "content": [
      "關洛蕭條南渡日，龜山往事屬龍津。",
      "過庭詩禮傳宗旨，蓋世功名付後人。",
      "風憲隻身中與外，清忠壯節晚如新。",
      "崇蘭香歇玉剛折，定與天皇作侍臣。"
    ]
  },
  {
    "title": "代王維謹挽李察院二首  其二",
    "author": "黄榦",
    "content": [
      "牛角短歌頭半白，龍門峻級眼常青。",
      "一官多是春風力，千里俄驚秋淚零。",
      "坐想德容今寂寞，夢回耳語尚丁寧。",
      "夜臺雖閉公長在，有子能存舊典刑。"
    ]
  },
  {
    "title": "端午五言三首  其一",
    "author": "劉克莊",
    "content": [
      "綺紈貴家子，旗鼓少年場。",
      "屢舞衆人醉，鮮粧一國狂。"
    ]
  },
  {
    "title": "端午五言三首  其二",
    "author": "劉克莊",
    "content": [
      "士女匆匆散，溪山寂寂然。",
      "龍舟閑似我，閣起向沙邊。"
    ]
  },
  {
    "title": "端午五言三首  其三",
    "author": "劉克莊",
    "content": [
      "雜遝今觀渡，依稀昔浴沂。",
      "居人空巷出，幾箇詠而歸。"
    ]
  },
  {
    "title": "代挽王潜齋  其一",
    "author": "王柏",
    "content": [
      "自立西山雪，聲名四十年。",
      "清思奎畫重，忠簡物情憐。",
      "廊廟風雲斷，園林歲月遷。",
      "潜齋元不死，有子續遺編。"
    ]
  },
  {
    "title": "代挽王潜齋  其二",
    "author": "王柏",
    "content": [
      "先世論交早，名公不忍忘。",
      "共期霖雨施，忽掩斗樞光。",
      "北墅風煙慘，南山草木香。",
      "片雲開白日，卹典耀龍㡛。"
    ]
  },
  {
    "title": "洞微翁挽章",
    "author": "釋行海",
    "content": [
      "凄凉木末搴芙蓉，萬里鷹揚路忽窮。",
      "箭到紅心翻墮地，花成綠子又隨風。",
      "可憐玉兔沉滄海，却放寒烏占碧桐。",
      "萬事看來都是夢，山林猶憶舊英雄。"
    ]
  },
  {
    "title": "悼無文和尚",
    "author": "釋月磵",
    "content": [
      "玉几深深結死冤，錯傳一印漫無文。",
      "春雷轟破轟不破，盡盡江天飛暮雲。"
    ]
  },
  {
    "title": "都尉王居士贊",
    "author": "楊傑",
    "content": [
      "珠圎而明，玉澤而温。",
      "鑑瑩澈而絕塵，芝秀發而非根。",
      "曼殊沙華，栴檀香芬。",
      "晦堂路險，大開施門。",
      "西江水深，一口平吞。",
      "誰知威音已前，正是王老師孫。"
    ],
    "meta": {
      "tags": [
        "长江"
      ]
    }
  },
  {
    "title": "答無爲居士楊傑",
    "author": "釋本嵩",
    "content": [
      "情智何嘗異，犬吠蛇自行。",
      "終南的的意，日午打三更。"
    ]
  },
  {
    "title": "答文翁",
    "author": "沈遼",
    "content": [
      "陶令初尋彭澤來，相如已構臨邛臺。",
      "正當銜杯行樂事，惠我鴻筆何爲哉。",
      "湖中多魚近易捕，石上老蕨拳未開。",
      "夫子不肯至我室，行駕畫舸遙相陪。"
    ]
  },
  {
    "title": "答王文舉",
    "author": "賀鑄",
    "content": [
      "茫茫塵土欲安之，珍重吾人箇處期。",
      "綠野相隨一藜杖，青山正對兩茅茨。",
      "自憐悾惚負平昔，尚敢婆娑臨暮遲。",
      "第恐阿戎猶喜仕，它時不與五君詩。"
    ]
  },
  {
    "title": "讀王文正遺事",
    "author": "王十朋",
    "content": [
      "太平宰相王文正，盛德真宜有子孫。",
      "舊國今餘幾喬木，三槐陰滿宋乾坤。"
    ]
  },
  {
    "title": "荅王無功冬夜載酒鄉館",
    "author": "崔善爲",
    "content": [
      "頒條忝貴郡，懸榻久相望。",
      "處士同楊鄭，邦君謝李疆。",
      "詎知方擁篲，逢子敬惟桑。",
      "明朝蓬戶側，會自謁任棠。"
    ]
  },
  {
    "title": "荅王無功九日",
    "author": "崔善爲",
    "content": [
      "秋來菊花氣，深山客重尋。",
      "露葉疑涵玉，風花似散金。",
      "摘來還泛酒，獨坐即徐斟。",
      "王弘貪自醉，無復覓楊林。"
    ]
  },
  {
    "title": "荅王無功問故園",
    "author": "朱仲晦",
    "content": [
      "我從銅州來，見子上京客。",
      "問我故鄉事，慰子羈旅色。",
      "子問我所知，我對子應識。",
      "朋遊總強健，童稚各長成。",
      "華宗盛文史，連牆富池亭。",
      "獨子園最古，舊林間新坰。",
      "柳行隨堤勢，茅齋看地形。",
      "竹從去年移，梅是今年榮。",
      "渠水經夏響，石苔終歲青。",
      "院果早晚熟，林花先後明。",
      "語罷相歎息，浩然起深情。",
      "歸哉且五斗，餉子東皐耕。"
    ]
  },
  {
    "title": "荅王無功入長安詠秋蓬見示",
    "author": "辛學士",
    "content": [
      "托根雖異所，飄葉早相依。",
      "因風若有便，更共入雲飛。"
    ]
  },
  {
    "title": "登無爲冠鰲亭分韻得山字",
    "author": "李流謙",
    "content": [
      "岱嵩拆裂滄溟翻，驚魂去幹呼復還。",
      "故人勸我勉自寬，聖貴揚名懲毀殘。",
      "十生導師超物先，誓言一拜蠲冤煩。",
      "曉暾破霽山雲搴，匹馬弄袖風翩翩。",
      "解鞍投寺日幾磚，莧蔬宜我詩腸酸。",
      "危亭飛出峯之巔，闍黎慇懃勸躋攀。",
      "我飽聞之意欣然，兩脚酸澀怯不前。",
      "清景一失矢縱弦，藜杖到手勿作難。",
      "萬杉夾逕穿蜿蜒，坦如康莊駕輕軿。",
      "山鬼作意發天慳，似求清詩藻幽妍。",
      "憑欄寸目攝大千，萬里碧玉圍青天。",
      "遠樹如髮山如拳，孤鴻滅沒昏蒼烟。",
      "九關上羾須臾還，以氣爲馬不用鞭。",
      "冠鼇榜亭固寓言，亦恐蓬嶠神作遷。",
      "雲旗往往來飛仙，切勿投餌憂崩騫。",
      "壯哉古邑雄兩川，眇然下瞰廼爾孱。",
      "可憐居人蟻紛闐，擾擾膏火日夜煎。",
      "强弱角鬭觸與蠻，豈知共住一指端。",
      "憑誰與此曠蕩觀，定當泚顙頳厥顔。",
      "向來學道窺微玄，妙諦與世殊越燕。",
      "空生大覺海一涓，而况此境空所緣。",
      "摩尼流光照八埏，試將此理攻堅頑。",
      "客言有句子未參，一杯滿酌澆青山。"
    ]
  },
  {
    "title": "弔無爲照老三首  其一",
    "author": "李流謙",
    "content": [
      "彈指超然一念初，從儒從佛兩蘧廬。",
      "十年身走半天下，萬卷人稱行祕書。",
      "故自高懷嫌入俗，不妨兒輩共憎渠。",
      "臨行半偈如何道，裂轉虛空最起予。"
    ]
  },
  {
    "title": "弔無爲照老三首  其二",
    "author": "李流謙",
    "content": [
      "記得三溪溪上春，瘦筇容我夜敲門。",
      "一生幾見此人物，十日九從師笑言。",
      "閒得得來非有意，冷湫湫去若爲論。",
      "西山第一烟雲窟，好駐高人雪月魂。"
    ]
  },
  {
    "title": "弔無爲照老三首  其三",
    "author": "李流謙",
    "content": [
      "六尺巖巖鐵石姿，可憐一病不支持。",
      "荒榛半壠獨歸處，暝靄數峯無見時。",
      "未割塵緣聊洒涕，欲尋陳迹但哦詩。",
      "蕭蕭秋雨山中夜，負我他年對榻期。"
    ]
  },
  {
    "title": "答王維留宿",
    "author": "祖詠",
    "content": [
      "四年不相見，相見復何爲。",
      "握手言未畢，却令傷別離。",
      "升堂還駐馬，酌醴便呼兒。",
      "語嘿自相對，安用傍人知。"
    ]
  },
  {
    "title": "答王無功在京思故園見鄉人問",
    "author": "朱熹",
    "content": [
      "我從銅川來，見子上京客。",
      "問我故鄉事，慰子覊旅色。",
      "子問我所知，我對子應識。",
      "朋遊總彊𡏖，童稚各長成。",
      "華宗盛文史，連牆富池亭。",
      "獨子園最古，舊林間新坰。",
      "柳行隨堤勢，茅齋看地形。",
      "竹從去年移，梅是今年榮。",
      "渠水經夏響，石苔終歲青。",
      "院果早晚熟，林花先後明。",
      "語罷相歎息，浩然起深情。",
      "歸哉且五斗，餉子東臯耕。"
    ]
  },
  {
    "title": "答王無功冬夜載酒鄉館",
    "author": "崔善為",
    "content": [
      "頒條忝貴郡，懸榻久相望。處士同楊鄭，邦君謝李疆。",
      "詎知方擁彗，逢子敬惟桑。明朝蓬戶側，會自謁任棠。"
    ]
  },
  {
    "title": "答王無功九日",
    "author": "崔善為",
    "content": [
      "秋來菊花氣，深山客重尋。露葉疑涵玉，風花似散金。",
      "摘來還泛酒，獨坐即徐斟。王弘貪自醉，無複覓楊林。"
    ]
  },
  {
    "title": "答王無功問故園",
    "author": "朱仲晦",
    "content": [
      "我從銅州來，見子上京客。問我故鄉事，慰子羈旅色。",
      "子問我所知，我對子應識。朋游總強健，童稚各長成。",
      "華宗盛文史，連牆富池亭。獨子園最古，舊林間新坰。",
      "柳行隨堤勢，茅齋看地形。竹從去年移，梅是今年榮。",
      "渠水經夏響，石苔終歲青。院果早晚熟，林花先後明。",
      "語罷相歎息，浩然起深情。歸哉且五鬥，餉子東皋耕。"
    ]
  },
  {
    "title": "答王維留宿",
    "author": "祖詠",
    "content": [
      "四年不相見，相見複何為。握手言未畢，卻令傷別離。",
      "升堂還駐馬，酌醴便呼兒。語嘿自相對，安用傍人知。"
    ]
  },
  {
    "title": "答王無功入長安詠秋蓬見示",
    "author": "辛學士",
    "content": [
      "托根雖異所，飄葉早相依。因風若有便，更共入雲飛。"
    ]
  }
]