[
  {
    "title": "蘭亭題詠  其一",
    "author": "李兼",
    "content": [
      "書法光芒晉永和，後來摹寫不勝多。",
      "考論又得桑夫子，蘭渚風流轉不磨。"
    ]
  },
  {
    "title": "蘭亭題詠  其二",
    "author": "李兼",
    "content": [
      "自從繭紙殉昭陵，定武流傳賸得名。",
      "總輯舊聞爲博議，即今真贋不難憑。"
    ]
  },
  {
    "title": "林屯田思軒",
    "author": "李覯",
    "content": [
      "慮遠無如靜，茲軒得地幽。",
      "一官雖智效，萬仞更心游。",
      "風月趨吟筆，乾坤入坐籌。",
      "延英期上對，豈是爲身謀。"
    ]
  },
  {
    "title": "留題泰山孫復先生新居",
    "author": "祖無擇",
    "content": [
      "築室新成日觀前，亂雲重疊稱高眠。",
      "人逢捫蝨驚旁若，衆望乘駒詠賁然。",
      "名理靜談誰捉麈，古書閒校自磨鉛。",
      "行聞天子東巡狩，羽葆親臨此禮賢。"
    ],
    "meta": {
      "tags": [
        "泰山"
      ]
    }
  },
  {
    "title": "留題天樂寓張氏湖亭",
    "author": "陳起",
    "content": [
      "沉水香銷一局棋，客來淺酌旋分題。",
      "畫欄占得春多少，簾捲東風日未西。"
    ]
  },
  {
    "title": "覽天童示寂偈",
    "author": "釋慧空",
    "content": [
      "太白峰前青海尾，一目秋光彌萬里。",
      "漁翁醉入蘆花深，白鳥不飛天在水。"
    ]
  },
  {
    "title": "留題唐棲寺",
    "author": "周弼",
    "content": [
      "僧房十日相留戀，爲怯生寒未到家。",
      "插岸斷冰妨蕩槳，入簷飛雪助煎茶。",
      "香臺穴碎逃秋蟻，古殿巢翻失暮鴉。",
      "惟有溪梅最禁耐，傍籬爭發向陽花。"
    ]
  },
  {
    "title": "留題天遊閣",
    "author": "陳襄",
    "content": [
      "誰榜天遊向此軒，欲令幽隠味真篇。",
      "一心泯絕渾無計，萬事攖寧付自然。",
      "持鉢隨緣朝乞供，閉門扣寂夜安禪。",
      "如師早契南華旨，即是逍遥物外仙。"
    ]
  },
  {
    "title": "留題太平寺",
    "author": "强至",
    "content": [
      "鄉落少人煙，精廬獨巋然。",
      "香花真佛界，棟宇始唐年。",
      "鳥啄齋餘食，僧參夜半禪。",
      "清凉數畝地，已是隔塵緣。"
    ]
  },
  {
    "title": "凌屯田知和州",
    "author": "宋祁",
    "content": [
      "坡殿程篇屬思精，飄飄老氣薄黔嬴。",
      "一臺舊服郎官筆，千騎新提太守兵。",
      "候吏騰裝催去舸，故人引脰悵離觥。",
      "雲波莫苦秋江闊，自有桃歌用檝迎。"
    ]
  },
  {
    "title": "留題桐柏石道師妙聲堂次曾史君韵",
    "author": "石延慶",
    "content": [
      "一派奔湍響迅雷，噴雲翻雪繞瓊臺。",
      "應通天上銀潢路，準擬乘槎八月來。"
    ]
  },
  {
    "title": "留題天繪亭",
    "author": "鄒浩",
    "content": [
      "杖屨追隨陟杳冥，無邊勝景集孤亭。",
      "解衣自若誰爲史，造物難窮巧賦形。",
      "展拓二儀成縞素，均調一氣作丹青。",
      "會將斷取山川手，卷入中州挂戶庭。"
    ]
  },
  {
    "title": "留題太山",
    "author": "倪適",
    "content": [
      "下列羣山谷萬道，霞瑞重重絕頂高。",
      "獨判天涯第一□，洞天深影無人□。"
    ]
  },
  {
    "title": "留題天寧明極堂",
    "author": "李綱",
    "content": [
      "久客若飛蓬，年年氣味同。",
      "猶欣容榻地，更得化人宫。",
      "鬰勃炎蒸極，巍峨棟宇雄。",
      "疏林碎搖月，虚館迥含風。",
      "萬户軒楹外，三山指顧中。",
      "靈潮自朝夕，大舶各西東。",
      "悵望關河遠，蒼茫雲海空。",
      "餘生寄閑曠，任運學龐翁。"
    ]
  },
  {
    "title": "盧頭陀詩",
    "author": "元稹",
    "content": [
      "盧師深話出家由，剃盡心花始剃頭。",
      "馬哭青山別車匿，鵲飛螺髻見羅睺。",
      "還來舊日經過處，似隔前身夢寐游。",
      "爲向八龍兄弟說，他生緣會此生休。"
    ]
  },
  {
    "title": "留題天竺靈隱兩寺",
    "author": "白居易",
    "content": [
      "在郡六百日，入山十二回。",
      "宿因月桂落，醉爲海榴開。",
      "黃紙除書到，青宮詔命催。",
      "僧徒多悵望，賓從亦裴回。",
      "寺闇煙埋竹，林香雨落梅。",
      "別橋憐白石，辭洞戀青苔。",
      "漸出松間路，猶飛馬上桮。",
      "誰教冷泉水，送我下山來。"
    ]
  },
  {
    "title": "隴亭童謠",
    "author": "佚名",
    "content": [
      "秦隴無人塞草青，將軍一去泣空營。",
      "漢家天子車巡狩，行到江南又起兵。",
      "（《記纂淵海》卷二十五）。"
    ]
  },
  {
    "title": "劉蛻唐大中時人文塚在兜率寺予嘗讀孫樵自序其作云大中皇帝嘗有詔褒時之藝能凡三人而樵居其一曰孫樵有揚馬之文蛻既同時不應不在褒詔之列士之顯晦固有定分劉君獨未能忘此乎塚其文予蓋疑其有激也作此弔之",
    "author": "李流謙",
    "content": [
      "詔書嘗下大中朝，不聞稱蛻但稱樵。",
      "犠樽棄溝俱害性，此理要以達觀超。",
      "封文爲塚嬉笑怒，恚不人知防鬼妬。",
      "高岸爲谷谷爲陵，磨滅可無千載慮。",
      "向來述作等俳諧，傳與不傳何有哉。",
      "六經排孔諱服鄭，未勝咸陽一炬灰。",
      "虛名誤人箕斗爾，引調狙公嗔與喜。",
      "已嗤地下有修文，更笑樓成能作記。"
    ]
  },
  {
    "title": "留題太山",
    "author": "倪適",
    "content": [
      "下列羣山谷萬道，霞瑞重重絕頂高。",
      "獨判天涯第一□，洞天深影無人□。"
    ]
  },
  {
    "title": "隴亭童謠",
    "author": "佚名",
    "content": [
      "秦隴無人塞草青，將軍一去泣空營。",
      "漢家天子車巡狩，行到江南又起兵。",
      "（《記纂淵海》卷二十五）。"
    ]
  },
  {
    "title": "劉屯田墓壯節亭",
    "author": "尤袤",
    "content": [
      "西澗當年卜考槃，便於神武掛衣冠。",
      "後生無復知前輩，故老猶能說長官。",
      "三尺荒墳埋玉冷，百年壯節倚天寒。",
      "表章頼有羣賢力，誰把生芻奠酒盤。"
    ]
  },
  {
    "title": "盧頭陀詩",
    "author": "元稹",
    "content": [
      "盧師深話出家由，剃盡心花始剃頭。馬哭青山別車匿，",
      "為向八龍兄弟說，他生緣會此生休。"
    ]
  },
  {
    "title": "留題天竺、靈隱兩寺",
    "author": "白居易",
    "content": [
      "在郡六百日，入山十二回。宿因月桂落，醉為海榴開。",
      "黃紙除書到，青宮詔命催。僧徒多悵望，賓從亦裴回。",
      "寺闇煙埋竹，林香雨落梅。別橋憐白石，辭洞戀青苔。",
      "漸出松間路，猶飛馬上杯。誰教冷泉水，送我下山來。"
    ]
  }
]