[
  {
    "title": "南曲风人松",
    "author": "萧德祥《小孙屠》",
    "content": [
      "记前日席上泛绿蚁，做夫妻永同连理。",
      "谁知每日贪欢会？醺醺地不思量归计。",
      "你那里谁人共美？教奴自守孤帏。",
      "(又唱)。"
    ]
  },
  {
    "title": "南曲风人松",
    "author": "萧德祥《小孙屠》",
    "content": [
      "我一心指望你攻书。",
      "要改换门闾。",
      "如今把奴成抛弃，朝朝望朝朝不至。",
      "好教人鸳衾坦冷落，须闲了我一个枕头儿。",
      "(又唱)。"
    ]
  },
  {
    "title": "南曲风人松",
    "author": "萧德祥《小孙屠》",
    "content": [
      "细思量教我泪双垂，使奴虚度良时。",
      "绣房懒入拈针指，终朝里没情没绪。",
      "枕屏边声声叫你，情脉咏转九语。",
      "(又唱)。"
    ]
  },
  {
    "title": "南曲风人松",
    "author": "萧德祥《小孙屠》",
    "content": [
      "看刘伶酒自半醒时，不似你沉醉如泥。",
      "当初李白曾题记，它得遇唐朝皇帝。",
      "(白)李太白醉时，杨妃捧砚，力士脱靴，龙巾拭唾，御手调羹。",
      "今日也是醉，(唱)枉教人千般告你，别寻个解绦底。"
    ]
  },
  {
    "title": "南曲锦缠道",
    "author": "萧德祥《小孙屠》",
    "content": [
      "奔行程，哀哀不曾住声，各不定珠泪如倾。",
      "挑着个纸幡儿，招展痛苦伤情。",
      "这骨匣一回价又轻，一回价又觉还沉。",
      "莫不是亲母显威灵，娘相扶相随，相佑到帝京。",
      "到得家中后，见哥哥诉元因。",
      "(唱)。"
    ]
  },
  {
    "title": "南曲刷子序",
    "author": "萧德祥《小孙屠》",
    "content": [
      "心中自忖，怨亲娘可煞孤命。",
      "你若家里死后，便累七追享，不免请几个僧人。",
      "止不过做两三夜道场，看几卷忏文《心经》。",
      "暗自省也落得草草，出殡在西城。"
    ]
  },
  {
    "title": "南泉",
    "author": "韓淲",
    "content": [
      "白雲洞邊流水聲，春風桃李鳥和鳴。",
      "客來掃塔無餘事，一宿僧房詩思生。"
    ]
  },
  {
    "title": "南七寺",
    "author": "方信孺",
    "content": [
      "井軫南宮煥寶光，千秋古勝並延祥。",
      "祗今兩寺無名字，地藏旁聯四實方。"
    ]
  },
  {
    "title": "內前  其一",
    "author": "王同祖",
    "content": [
      "兩桁垂楊護九重，翠眉羞畫舊隋宮。",
      "柔條似怕君恩重，低拂朱欄舞曉風。"
    ]
  },
  {
    "title": "內前  其二",
    "author": "王同祖",
    "content": [
      "麗正門開曉色鮮，萬絲綠柳御溝邊。",
      "禁中恐有題紅怨，不放涓流出內前。"
    ]
  },
  {
    "title": "南蹌跧上人之平江",
    "author": "俞桂",
    "content": [
      "青浦相逢恰二年，今宵再會亦前緣。",
      "詩囊和月橫挑去，穩泛楓橋夜半船。"
    ]
  },
  {
    "title": "南橋",
    "author": "釋紹曇",
    "content": [
      "渡馿渡馬已多時，踏斷何妨入水泥。",
      "贍部洲人爭弄險，要渠知有截流機。"
    ]
  },
  {
    "title": "甯戚飯牛圖",
    "author": "鄭思肖",
    "content": [
      "斯人豈是飯牛者，浩歎空懷扣角悲。",
      "說到漫漫長夜處，南山白石也攢眉。"
    ]
  },
  {
    "title": "瘧起舍弟尚未已示道原",
    "author": "王安石",
    "content": [
      "側足呻吟地，連甍瘴瘧秋。",
      "窮鄉醫自絀，小市藥難求。",
      "肝膽疑俱破，筋骸漫獨瘳。",
      "慚君遠從我，契闊每同憂。"
    ]
  },
  {
    "title": "內前行",
    "author": "唐庚",
    "content": [
      "內前車馬撥不開，文德殿下宣麻回。",
      "紫薇侍郎拜右相，中使押赴文昌臺。",
      "旄頭昨夜光照牖，是夕收芒如禿帚。",
      "明日化爲甘雨來，宅家喚作調元手。",
      "周公禮樂未要作，致身姚宋也不惡。",
      "向來兩翁當國年，民間斗米纔四錢。"
    ]
  },
  {
    "title": "南遷",
    "author": "唐庚",
    "content": [
      "去去寛鄉託此蹤，閙中無地頓衰翁。",
      "未誅綺語猶輕典，更賜羅浮有底功。",
      "蝦菜賤時皆丙穴，茅柴美處即郫筒。",
      "著鞭要及春前到，趁賦梅花庾嶺東。"
    ]
  },
  {
    "title": "擬青青河畔草",
    "author": "周紫芝",
    "content": [
      "四序相推遷，日月倏已逝。",
      "春風入猗蘭，光艶照羅綺。",
      "一朝霜雪至，容華苦憔悴。",
      "佳人惜朱顔，結褵奉君子。",
      "安知遠征途，中道成棄置。",
      "昔持鴛鴦錦，裁成合歡被。",
      "今織迴文機，中有相思字。",
      "相思日夜切，尺書無雁寄。",
      "誰能知妾心，脈脈含遠意。"
    ]
  },
  {
    "title": "南遷道鬱林郡守王君示古律詩一篇北歸輙成兩篇以答其意  其一",
    "author": "李綱",
    "content": [
      "山圍古郡碧周遭，陸績衣冠雅自襃。",
      "海上來歸懷麈尾，鬢間空歎長霜毛。",
      "易書顧我耽成癖，詩筆憐君老更豪。",
      "此去龍城幸非遠，不須巨石壓雲濤。"
    ]
  },
  {
    "title": "南遷道鬱林郡守王君示古律詩一篇北歸輙成兩篇以答其意  其二",
    "author": "李綱",
    "content": [
      "垂老相逢海嶠間，盈編珠玉破愁顔。",
      "清名豈籍鬱林石，雅志常存仙奕山。",
      "丘壑採薇嗟我病，絃歌爲政羡君閒。",
      "中原杳杳旌旗暗，迴首春風涕一澘。"
    ]
  },
  {
    "title": "年侵",
    "author": "晁公遡",
    "content": [
      "年侵慵更甚，帙亂卷還舒。",
      "衰白愁看鏡，雌黄倦校書。",
      "臨風知地爽，映日愛窗虛。",
      "近報畬田粟，洿邪亦滿車。"
    ]
  },
  {
    "title": "南齊",
    "author": "陳洎",
    "content": [
      "曲江歡宴侍華裾，舞拍琴歌藝有餘。",
      "獨有純臣王叔寶，解陳封禪一篇書。"
    ]
  },
  {
    "title": "南泉",
    "author": "趙鼎",
    "content": [
      "陰液淪山顛，天匠鑿其腹。",
      "噴薄湧飛泉，散落珠百斛。",
      "幽人時一來，但愛消煩溽。",
      "何當作膏雨，萬里蒙霡霂。"
    ]
  },
  {
    "title": "南遷途中作七首 登七盤嶺二首 一",
    "author": "吳融",
    "content": [
      "才非賈傅亦遷官，五月驅羸上七盤。",
      "從此自知身計定，不能迴首望長安。"
    ]
  },
  {
    "title": "南遷途中作七首 登七盤嶺二首 二",
    "author": "吳融",
    "content": [
      "七盤嶺上一長號，將謂青天鑒鬱陶。",
      "近日青天都不鑒，七盤應是未高高。"
    ]
  },
  {
    "title": "南遷途中作七首 渡漢江初嘗鯿魚有作",
    "author": "吳融",
    "content": [
      "嘯父知機先憶魚，季[鷹]無事已思鱸。",
      "自慙初識查頭味，正是栖栖哭阮塗。"
    ]
  },
  {
    "title": "南遷途中作七首 溪翁",
    "author": "吳融",
    "content": [
      "飯稻羹菰曉復昏，碧灘聲裏長諸孫。",
      "應嗟獨上涔陽客，排比椒漿奠楚魂。"
    ]
  },
  {
    "title": "南遷途中作七首 寄友人",
    "author": "吳融",
    "content": [
      "驚魂往往坐疑飄，便好爲文慰寂寥。",
      "若待清湘葬魚了，縱然招得不堪招。"
    ]
  },
  {
    "title": "南遷途中作七首 塗中偶懷",
    "author": "吳融",
    "content": [
      "無路能酬國士恩，短亭寂寂到黃昏。",
      "迴腸一寸危如綫，賴得商山未有猨。"
    ]
  },
  {
    "title": "南遷途中作七首 訪貫休上人",
    "author": "吳融",
    "content": [
      "休公爲我設蘭湯，方便教人學洗腸。",
      "自覺塵纓頓瀟灑，南行不復問滄浪。"
    ]
  },
  {
    "title": "擬齊梁酬所知見贈二首 一",
    "author": "貫休",
    "content": [
      "靜只焚香坐，詠懷悲歲闌。",
      "佳人忽有贈，滿手紅琅玕。",
      "不獨耀肌魄，將行爲羽翰。",
      "酬如上青天，風雪空漫漫。"
    ]
  },
  {
    "title": "擬齊梁酬所知見贈二首 二",
    "author": "貫休",
    "content": [
      "美如仙鼎金，清如纖手琴。",
      "孫登嘯一聲，縹緲不可尋。",
      "但覺神洋洋，如入三昧林。",
      "釋手復在手，古意深復深。",
      "慚無英瓊瑤，何以酬知音。"
    ]
  },
  {
    "title": "擬齊梁體寄馮使君三首 一",
    "author": "貫休",
    "content": [
      "庭鳥多好音，相呼灌木中。",
      "竹房更何有，還如鳥巢空。",
      "賴逢富人侯，真東晉謝公。",
      "煌煌發令姿，珂珮鳴丁冬。",
      "故山有深霞，未如旌旗紅。",
      "慚非衛霍松，何以當清風。"
    ]
  },
  {
    "title": "擬齊梁體寄馮使君三首 二",
    "author": "貫休",
    "content": [
      "露益蟬聲長，蕙蘭垂紫帶。",
      "清吟代明月，孤雲忽爲蓋。",
      "伊余石林人，本是燒畬輩。",
      "頻接謝公棊，輸多未曾賽。"
    ]
  },
  {
    "title": "擬齊梁體寄馮使君三首 三",
    "author": "貫休",
    "content": [
      "大道貴無心，聖賢爲始慕。",
      "秋空共澄潔，美玉同貞素。",
      "偉哉桐江守，雌黃出金口。",
      "爲文能廢興，談道弭空有。",
      "雪林槁枯者，坐石聽亦久。",
      "還疑紫磨身，成居靈運後。"
    ]
  },
  {
    "title": "擬權龍褒體贈鄠縣李令及寄朝右",
    "author": "鄭愚",
    "content": [
      "鄠縣李長官，橫琴膝上弄。",
      "不聞有政聲，但見手子動。"
    ]
  },
  {
    "title": "南遷至衡嶽贈全玼詩（題擬）",
    "author": "孫偓",
    "content": [
      "窠居過後更何人，傳得如來法印真。",
      "昨日祝融峰下見，草衣便是雪山身。",
      "（見《宋高僧傳》卷三十）（按：《全唐詩》卷六八八收此詩，有缺文，今重錄。",
      "）。"
    ]
  },
  {
    "title": "南泉竹",
    "author": "剋符道者",
    "content": [
      "根蔕欲何尋？孤奇迥衆林。",
      "鳳來敲節目，龍去曉知音。",
      "撼雪精神別，吟風體物深。",
      "平常烟靄裏，動轉桭虛心。"
    ]
  },
  {
    "title": "南遷途中作七首 渡漢江初嘗鯿魚有作",
    "author": "吳融",
    "content": [
      "嘯父知機先憶魚，季[鷹]無事已思鱸。",
      "自慙初識查頭味，正是栖栖哭阮塗。"
    ]
  },
  {
    "title": "南遷至衡嶽贈全玼詩（題擬）",
    "author": "孫偓",
    "content": [
      "窠居過後更何人，傳得如來法印真。",
      "昨日祝融峰下見，草衣便是雪山身。",
      "（見《宋高僧傳》卷三十）（按：《全唐詩》卷六八八收此詩，有缺文，今重錄。",
      "）。"
    ]
  },
  {
    "title": "內丘梨園",
    "author": "范成大",
    "content": [
      "汗後鵝梨爽似冰，花身耐久老猶榮。",
      "園翁指似還三笑，曾共翁身見太平。"
    ]
  },
  {
    "title": "甯橋小渡",
    "author": "楊萬里",
    "content": [
      "橋壞仍泥滑，舟橫隔水呼。",
      "岸頭危徑窄，轎子莫人扶。",
      "午漏相將裏，秋陽未肯無。",
      "明知近前店，暗覺展脩途。"
    ]
  },
  {
    "title": "南遷途中作七首：登七盤嶺二首",
    "author": "吳融",
    "content": [
      "才非賈傅亦遷官，五月驅羸上七盤。",
      "從此自知身計定，不能回首望長安。",
      "七盤嶺上一長號，將謂青天鑒郁陶。",
      "近日青天都不鑒，七盤應是未高高。"
    ]
  },
  {
    "title": "南遷途中作七首：渡漢江初嘗鯿魚有作",
    "author": "吳融",
    "content": [
      "嘯父知機先憶魚，季鷹無事已思鱸。",
      "自慚初識查頭味，正是棲棲哭阮塗。"
    ]
  },
  {
    "title": "南遷途中作七首：溪翁",
    "author": "吳融",
    "content": [
      "飯稻羹菰曉複昏，碧灘聲裏長諸孫。",
      "應嗟獨上涔陽客，排比椒漿奠楚魂。"
    ]
  },
  {
    "title": "南遷途中作七首：寄友人",
    "author": "吳融",
    "content": [
      "驚魂往往坐疑飄，便好為文慰寂寥。",
      "若待清湘葬魚了，縱然招得不堪招。"
    ]
  },
  {
    "title": "南遷途中作七首：途中偶懷",
    "author": "吳融",
    "content": [
      "無路能酬國士恩，短亭寂寂到黃昏。",
      "回腸一寸危如線，賴得商山未有猿。"
    ]
  },
  {
    "title": "南遷途中作七首：訪貫休上人",
    "author": "吳融",
    "content": [
      "休公為我設蘭湯，方便教人學洗腸。",
      "自覺塵纓頓瀟灑，南行不復問滄浪。"
    ]
  },
  {
    "title": "擬齊梁酬所知見贈二首",
    "author": "貫休",
    "content": [
      "靜只焚香坐，詠懷悲歲闌。佳人忽有贈，滿手紅琅玕。",
      "不獨耀肌魄，將行為羽翰。酬如上青天，風雪空漫漫。",
      "美如仙鼎金，清如纖手琴。孫登嘯一聲，縹緲不可尋。",
      "但覺神洋洋，如入三昧林。釋手複在手，古意深複深。",
      "慚無英瓊瑤，何以酬知音。"
    ]
  },
  {
    "title": "擬齊梁體寄馮使君三首",
    "author": "貫休",
    "content": [
      "庭鳥多好音，相呼灌木中。竹房更何有，還如鳥巢空。",
      "賴逢富人侯，真東晉謝公。煌煌發令姿，珂佩鳴丁冬。",
      "故山有深霞，未如旌旗紅。慚非衛霍松，何以當清風。",
      "露益蟬聲長，蕙蘭垂紫帶。清吟待明月，孤雲忽為蓋。",
      "伊余石林人，本是燒畬輩。頻接謝公棋，輸多未曾賽。",
      "大道貴無心，聖賢為始慕。秋空共澄潔，美玉同貞素。",
      "偉哉桐江守，雌黃出金口。為文能廢興，談道弭空有。",
      "雪林槁枯者，坐石聽亦久。還疑紫磨身，成居靈運後。"
    ]
  },
  {
    "title": "擬權龍褒體贈鄠縣李令及寄朝右",
    "author": "鄭愚",
    "content": [
      "鄠縣李長官，橫琴膝上弄。不聞有政聲，但見手子動。"
    ]
  }
]