[
  {
    "title": "送歸篇",
    "author": "釋文珦",
    "content": [
      "秋老木葉乾，露冷蟲聲死。",
      "征人未授衣，鄉心日千里。",
      "揮手睇雲帆，頃刻限煙水。",
      "他時慰相思，遠寄書一紙。"
    ]
  },
  {
    "title": "石鼓鋪",
    "author": "趙若槸",
    "content": [
      "山前山後杜鵑花，莊上黄鸝識謝家。",
      "欲問青帘溪上酒，行逢白髪道邊茶。"
    ]
  },
  {
    "title": "送廣平孫教授",
    "author": "陸文圭",
    "content": [
      "廣平河水北，古暨浙江南。",
      "兩地音郵闊，三年官况諳。",
      "采芹聊共樂，食蘗豈能甘。",
      "別酒黄梅浦，情懷老不堪。"
    ]
  },
  {
    "title": "送郭評事節判磨勘",
    "author": "黄庶",
    "content": [
      "塵埃衣襟改顔色，獨洗青衫三十年。",
      "足迹不入奔走途，來往銓戶鞋履穿。",
      "一時同上青雲人，往往裨補造化權。",
      "朝梳滿手見白髪，嘆息不置齒牙間。",
      "只言歸田有幾畝，種秫欲釀山中泉。",
      "腰邊即見佩銅墨，我喜百里瘡痍痊。"
    ]
  },
  {
    "title": "送公闢給事自州致政歸吳中",
    "author": "王珪",
    "content": [
      "青瑣仙人解玉符，秋風一夜滿江湖。",
      "曾歌郢水非凡曲，未掃旄頭負壯圖。",
      "終日望君天欲盡，平生知我世應無。",
      "扁舟定約元宫保，瀟灑蓮涇二大夫。"
    ]
  },
  {
    "title": "送公闢給事自青州致政歸吳中",
    "author": "鄭獬",
    "content": [
      "青瑣仙人解玉符，秋風一夜滿江湖。",
      "曾歌郢水非凡曲，未掃旄頭負壯圖。",
      "終日望君天欲盡，平生知我世應無。",
      "扁舟應約元宮保，瀟灑蓮涇二丈夫。"
    ]
  },
  {
    "title": "送郭判官赴振武",
    "author": "盧綸",
    "content": [
      "黃河九曲流，繚繞古邊州。",
      "鳴鴈飛初夜，羌胡正晚秋。",
      "淒涼金管思，迢遰玉人愁。",
      "七葉推多慶，須懷殺敵憂。"
    ],
    "meta": {
      "tags": [
        "黄河"
      ]
    }
  },
  {
    "title": "書郭判官幽齋壁",
    "author": "李中",
    "content": [
      "不妨公退尚清虛，剏得幽齋興有餘。",
      "要引好風清戶牖，旋栽新竹滿庭除。",
      "傾壺待客花開後，煮茗留僧月上初。",
      "更有野情堪愛處，石牀苔蘚似匡廬。"
    ],
    "meta": {
      "tags": [
        "庐山"
      ]
    }
  },
  {
    "title": "送郭僕射節制劒南",
    "author": "岑參",
    "content": [
      "鐵馬擐紅纓，幡旗出禁城。",
      "明王親授鉞，丞相欲專征。",
      "玉饌天廚送，金杯御酒傾。",
      "劒門乘嶮過，閣道踏空行。",
      "山鳥驚吹笛，江猿看洗兵。",
      "曉雲隨去陣，夜月逐行營。",
      "南仲今時往，西戎計日平。",
      "將心感知己，萬里寄懸旌。"
    ]
  },
  {
    "title": "送郭僕射節制劍南",
    "author": "岑參",
    "content": [
      "鐵馬擐紅纓，幡旗出禁城。明王親授鉞，丞相欲專征。",
      "玉饌天廚送，金杯禦酒傾。劍門乘嶮過，閣道踏空行。",
      "山鳥驚吹笛，江猿看洗兵。曉雲隨去陣，夜月逐行營。",
      "南仲今時往，西戎計日平。將心感知己，萬里寄懸旌。"
    ]
  },
  {
    "title": "送郭判官赴振武",
    "author": "盧綸",
    "content": [
      "黃河九曲流，繚繞古邊州。鳴雁飛初夜，羌胡正晚秋。",
      "淒涼金管思，迢遞玉人愁。七葉推多慶，須懷殺敵憂。"
    ]
  },
  {
    "title": "書郭判官幽齋壁",
    "author": "李中",
    "content": [
      "不妨公退尚清虛，創得幽齋興有餘。要引好風清戶牖，",
      "更有野情堪愛處，石床苔蘚似匡廬。"
    ]
  }
]