[
  {
    "title": "張端明挽詩  其一",
    "author": "薛季宣",
    "content": [
      "凋落傷前輩，風流屬老成。",
      "和羹方爾用，接淅已吾行。",
      "卜筮占先志，儀刑式後生。",
      "贈同開府相，哀誄易佳名。"
    ]
  },
  {
    "title": "張端明挽詩  其二",
    "author": "薛季宣",
    "content": [
      "帝功成贊育，天道與爲徒。",
      "祖帳霸陵岸，扁舟笠澤湖。",
      "送鞋非李泌，哭市有郇謨。",
      "已矣龍輀稅，依然曳尾塗。"
    ]
  },
  {
    "title": "贈杜默",
    "author": "歐陽修",
    "content": [
      "南山有鳴鳳，其音和且清。",
      "鳴於有道國，出則天下平。",
      "杜默東土秀，能吟鳳凰聲。",
      "作詩幾百篇，長歌仍短行。",
      "携之入京邑，欲使眾耳驚。",
      "來時上師堂，再拜辭先生。",
      "先生頷首遣，教以勿驕矜。",
      "贈之三豪篇，而我濫一名。",
      "杜子來訪我，欲求相和鳴。",
      "顧我文字卑，未足當豪英。",
      "豈如子之辭，鏗鍠間鏞笙。",
      "淫哇俗所樂，百鳥徒嚶嚶。",
      "杜子卷舌去，歸衫翩以輕。",
      "京東聚羣盜，河北點新兵。",
      "饑荒與愁苦，道路日以盈。",
      "子盍引其吭，發聲通下情。",
      "上聞天子聰，次使宰相聽。",
      "何必九包禽，始能瑞堯庭。",
      "子詩何時作，我耳入已傾。",
      "願以白玉琴，寫之朱絲繩。"
    ]
  },
  {
    "title": "自東門泛舟至竹西亭登崑丘入蒙谷戲題春貢亭",
    "author": "歐陽修",
    "content": [
      "崑丘蒙谷接新亭，畫舸悠悠春水生。",
      "欲覓揚州使君處，但隨風際管絃聲。"
    ]
  },
  {
    "title": "再禱梅山",
    "author": "華岳",
    "content": [
      "梅山昔扣五通仙，曾許英雄第一籤。",
      "恰遇塵埃當擾擾，如何泥濘尚淹淹。",
      "若非推入高宗夢，須是遥分太史占。",
      "他日崧高詠申甫，一香先爲大王拈。"
    ]
  },
  {
    "title": "讚達磨偈",
    "author": "釋元肇",
    "content": [
      "踏翻地軸與天關，合國人追不再還。",
      "去去一身輕似葉，長江千古浪如山。"
    ],
    "meta": {
      "tags": [
        "长江"
      ]
    }
  },
  {
    "title": "贊達磨",
    "author": "釋道顔",
    "content": [
      "五乳峰前，九年冷坐。",
      "孤風絕攀，名不敢涴。",
      "斷臂嗣芳，賤賣滯貨。",
      "螟蛉有子，負之蜾蠃。",
      "即說呪曰，類我類我。"
    ]
  },
  {
    "title": "舟到梅雨暴漲",
    "author": "朱繼芳",
    "content": [
      "夜月離于畢，篙師可奈何。",
      "帆穿風減半，江闊雨添多。",
      "側岸無牽路，中流有旋渦。",
      "平生柂樓底，得在柳梢過。"
    ]
  },
  {
    "title": "贈電眸陳相士",
    "author": "姚勉",
    "content": [
      "巖電當年說阿戎，清談于世竟何功。",
      "君今雙目真如電，舉世忠邪一覽中。"
    ]
  },
  {
    "title": "贈電目相士",
    "author": "何夢桂",
    "content": [
      "知君說相壓南州，相我空貽白髮羞。",
      "但得羊裘歸釣澤，安知燕頷去封侯。",
      "窮通有分都休問，出處難言已自謀。",
      "一笑相看出山去，逢人莫道見壺丘。"
    ]
  },
  {
    "title": "祚德廟",
    "author": "宋無",
    "content": [
      "祀典當時盛，忠曾保趙孤。",
      "誰知宋祚絕，今與廟俱無。"
    ]
  },
  {
    "title": "紫蔕梅",
    "author": "李龍高",
    "content": [
      "外面看來本色非，香袍隠映省垣薇。",
      "誰知傲睨風霜底，不改平生一布衣。"
    ]
  },
  {
    "title": "自東門泛舟至竹西亭登崑丘入蒙谷戲題二首  其一",
    "author": "劉敞",
    "content": [
      "汎汎扁舟春水平，緣蘋白芷欲齊生。",
      "王孫自喜山中客，莫唱淮南招隱聲。"
    ]
  },
  {
    "title": "自東門泛舟至竹西亭登崑丘入蒙谷戲題二首  其二",
    "author": "劉敞",
    "content": [
      "萬竿蒼翠隔晴川，寂寞蕪城三百年。",
      "此地重聞歌吹發，揚州風物故依然。"
    ]
  },
  {
    "title": "贊達磨大師",
    "author": "釋宗元",
    "content": [
      "十萬里來賣口嘴，宜乎打落當門齒，面壁九年誰採你。",
      "深雪之中若不得救苦救難觀世音菩薩，有甚面目歸鄉里。"
    ]
  },
  {
    "title": "姪端旻示遊浦江花藏寺詩且道皎老相問意因次韵併煩爲簡皎公禪師",
    "author": "范浚",
    "content": [
      "子到祇陀舍，經行幾屐穿。",
      "想當吟出月，不奈思如泉。",
      "真界飛花雨，寒山落木天。",
      "皎公知好在，香室夜安禪。"
    ]
  },
  {
    "title": "再答冕仲",
    "author": "黄庭堅",
    "content": [
      "丘壑詩書雖數窮，田園芋栗頗時豐。",
      "小桃源口雨繁紅，春溪蒲稗沒鳬翁。",
      "投身世網夢歸去，摘山鼓聲雷隠空。",
      "秋堂一笑共燈火，與公草木臭味同。",
      "安用茗澆壘塊胸，他日過飯隨家風，買魚貫柳雞著籠。",
      "更當力貧開酒椀，走謁鄰翁稱子本。"
    ]
  },
  {
    "title": "走答明略適堯民來相約奉謁故篇末及之",
    "author": "黄庭堅",
    "content": [
      "君不見生不願爲牛後，寧爲雞口。",
      "吾聞向來得道人，終古不忒如維斗。",
      "希價咸陽諸少年，可推令往挽令還。",
      "俗學風波能自拔，我識廖侯眉宇間。",
      "省庭無人與爭長，主司得之如受賞。",
      "東家一笑市盡傾，略無下蔡與陽城。",
      "生珠之水砂礫潤，生玉之山草木榮。",
      "觀君詞章亦如此，諒知躬行有君子。",
      "更約探囊閱舊文，蛛絲燈花助我喜。",
      "賢樂堂前竹影斑，好鳥自語莫令彈。",
      "北鄰著作相勞苦，整駕謁子邀同攀。",
      "應煩下榻煮茶藥，坐待月輪銜屋山。"
    ]
  },
  {
    "title": "再答明略二首  其一",
    "author": "黄庭堅",
    "content": [
      "挾策讀書計糊口，故人南箕與北斗。",
      "江南江北萬重山，千里寄書聲不還。",
      "當時朱弦寫心曲，果在高山深水間。",
      "枯桐滿腹生蛛網，忍向時人覓清賞。",
      "廖侯文字得我驚，五嶽縱橫守嚴城。",
      "萬夫之下不稱屈，定知名滿四海非真榮。",
      "富於春秋已如此，他日卜鄰長兒子。",
      "一丘各自有林泉，扶將白頭親燕喜。",
      "秋風日暮衣裳單，深巷落葉已如彈。",
      "數來會面復能幾，六龍去人不可攀。",
      "短歌溷公更一和，聊乞淮南作小山。"
    ]
  },
  {
    "title": "再答明略二首  其二",
    "author": "黄庭堅",
    "content": [
      "廖侯言如不出口，銓量古今膽如斗。",
      "度越崔張與二班，古風蕭蕭筆追還。",
      "前日辭家來射策，聲名藉甚諸公間。",
      "華陰白雲鎖千嶂，勝日一談誰能賞。",
      "君不見曩時子産識然明，知音鬰鬰閉佳城。",
      "勿以匣中之明月，計較糞上之朝榮。",
      "我去丘園十年矣，種桑可蠶犢生子。",
      "使年七十今中半，安能朝四暮三浪憂喜。",
      "據席談經只强顔，不安時論取譏彈。",
      "愛君草木同臭味，頗似瓜葛相依攀。",
      "我有仙方煮白石，何時期君藍田山。"
    ]
  },
  {
    "title": "贊達磨",
    "author": "釋守卓",
    "content": [
      "神光的的見聱訛，面壁喃喃語更多。",
      "不是梁王先勘破，脫身歸去奈渠何。"
    ]
  },
  {
    "title": "贈度門僧  其一",
    "author": "王庭珪",
    "content": [
      "眨起眉毛鐘已成，不容著手勒鐘銘。",
      "一鋪嶺上新功德，只欠將來點眼睛。"
    ]
  },
  {
    "title": "贈度門僧  其二",
    "author": "王庭珪",
    "content": [
      "半夜鐘聲殷寺廊，吹螺打鼓助錚鏦。",
      "不妨白日開門睡，更遣闍梨飯後撞。"
    ]
  },
  {
    "title": "贊達磨",
    "author": "釋法泰",
    "content": [
      "泛舶來梁自普通，一鎚擊碎有爲功。",
      "誰云面壁無言說，爭奈當門齒露風。"
    ]
  },
  {
    "title": "贈竇牟",
    "author": "楊憑",
    "content": [
      "直用天才衆却瞋，應欺李杜久爲塵。",
      "南荒不死中華老，別玉翻同西國人。"
    ]
  },
  {
    "title": "折得梅",
    "author": "鄭谷",
    "content": [
      "寒步江村折得梅，孤香不肯待春催。",
      "滿枝盡是愁人淚，莫殢朝來露溼來。"
    ]
  },
  {
    "title": "贊達磨",
    "author": "釋印肅",
    "content": [
      "妙契觸目菩提，誰觀達磨西歸。",
      "只是老胡捏怪，好與三十竹篦。",
      "試問參方知不知，狂書早自落便宜。"
    ]
  },
  {
    "title": "趙達明太社四月一日招遊西湖十首  其一",
    "author": "楊萬里",
    "content": [
      "今日清和和又清，王孫領客出都城。",
      "好天勝日能多少，三到西湖始一晴。"
    ],
    "meta": {
      "tags": [
        "西湖"
      ]
    }
  },
  {
    "title": "趙達明太社四月一日招遊西湖十首  其二",
    "author": "楊萬里",
    "content": [
      "畫舫侵晨繫柳枝，主人生怕客來遲。",
      "嬌雲嫩日無風色，幸是湖船好放時。"
    ],
    "meta": {
      "tags": [
        "西湖"
      ]
    }
  },
  {
    "title": "趙達明太社四月一日招遊西湖十首  其三",
    "author": "楊萬里",
    "content": [
      "船從詠澤過孤山，徑度琉璃一簟間。",
      "隔岸多情楊柳樹，向人招喚俯煙鬟。"
    ],
    "meta": {
      "tags": [
        "西湖"
      ]
    }
  },
  {
    "title": "趙達明太社四月一日招遊西湖十首  其四",
    "author": "楊萬里",
    "content": [
      "御池水滿苑門開，泥带飛花路带苔。",
      "到得孤山翻作惡，海棠閙日不曾來。"
    ],
    "meta": {
      "tags": [
        "西湖"
      ]
    }
  },
  {
    "title": "趙達明太社四月一日招遊西湖十首  其五",
    "author": "楊萬里",
    "content": [
      "萍生兒子點疎星，荷捲文書立萬丁。",
      "回首南高峰上塔，手中攀得玉竛竮。"
    ],
    "meta": {
      "tags": [
        "西湖"
      ]
    }
  },
  {
    "title": "趙達明太社四月一日招遊西湖十首  其六",
    "author": "楊萬里",
    "content": [
      "橘花如雪細吹香，杏子團枝未可嘗。",
      "行到陳朝枯柏處，孤山山背水中央。"
    ],
    "meta": {
      "tags": [
        "西湖"
      ]
    }
  },
  {
    "title": "趙達明太社四月一日招遊西湖十首  其七",
    "author": "楊萬里",
    "content": [
      "和靖先生墳已荒，空餘松竹故蒼蒼。",
      "王孫自洗鸕鷀杓，滿酌真珠酹一觴。"
    ],
    "meta": {
      "tags": [
        "西湖"
      ]
    }
  },
  {
    "title": "趙達明太社四月一日招遊西湖十首  其八",
    "author": "楊萬里",
    "content": [
      "行盡孤山碧四圍，却尋初路得來時。",
      "好風借與歸船便，吹近瓊林却不吹。"
    ],
    "meta": {
      "tags": [
        "西湖"
      ]
    }
  },
  {
    "title": "趙達明太社四月一日招遊西湖十首  其九",
    "author": "楊萬里",
    "content": [
      "風撩太液小荷欹，日麗長楊花影低。",
      "闌入苑中啼不歇，恨身不及一黄鸝。"
    ],
    "meta": {
      "tags": [
        "西湖"
      ]
    }
  },
  {
    "title": "趙達明太社四月一日招遊西湖十首  其一○",
    "author": "楊萬里",
    "content": [
      "葱蘢晚色正佳哉，苦被歸鞍緊緊催。",
      "船壓浮荷沈水底，須臾船過却浮來。"
    ],
    "meta": {
      "tags": [
        "西湖"
      ]
    }
  },
  {
    "title": "贈竇牟",
    "author": "楊憑",
    "content": [
      "直用天才眾卻瞋，應欺李杜久為塵。",
      "南荒不死中華老，別玉翻同西國人。"
    ]
  },
  {
    "title": "折得梅",
    "author": "鄭谷",
    "content": [
      "寒步江村折得梅，孤香不肯待春催。",
      "滿枝儘是愁人淚，莫殢朝來露濕來。"
    ]
  }
]